LICENSE
README.md
pyproject.toml
setup.py
monitor/monitor.c
pyrp3/__init__.py
pyrp3/board.py
pyrp3/client_memory.py
pyrp3/enum.py
pyrp3/instrument.py
pyrp3/memory.py
pyrp3/pc.py
pyrp3/raw_memory.py
pyrp3/service.py
pyrp3.egg-info/PKG-INFO
pyrp3.egg-info/SOURCES.txt
pyrp3.egg-info/dependency_links.txt
pyrp3.egg-info/requires.txt
pyrp3.egg-info/top_level.txt
tests/test_enum.py