Metadata-Version: 2.1
Name: pyrp3
Version: 2.1.0
Summary: Python utilities for RedPitaya
Author-email: Pierre Cladé <pierre.clade@upmc.fr>, Benjamin Wiegand <benjamin.wiegand@physik.hu-berlin.de>, Bastian Leykauf <leykauf@physik.hu-berlin.de>, Doron Behar <doron.behar@gmail.com>, Florian Agbuya <fa@m-labs.ph>
Maintainer-email: Bastian Leykauf <leykauf@physik.hu-berlin.de>
License: BSD 3-Clause License
Project-URL: homepage, https://github.com/linien-org/pyrp3/
Project-URL: repository, https://github.com/linien-org/pyrp3/
Keywords: RedPitaya,FPGA,zynq
Classifier: Programming Language :: Python :: 3
Classifier: License :: OSI Approved :: BSD License
Classifier: Operating System :: POSIX :: Linux
Classifier: Intended Audience :: Science/Research
Classifier: Intended Audience :: Education
Classifier: Topic :: Scientific/Engineering
Requires-Python: >=3.10
License-File: LICENSE
Requires-Dist: cached_property<2.0,>=1.5.2
Requires-Dist: numpy<2.0,>=1.21.5
Requires-Dist: rpyc<7.0,>=6.0.0
Provides-Extra: dev
Requires-Dist: black>=22.8.0; extra == "dev"
Requires-Dist: pre-commit>=2.20.0; extra == "dev"
Requires-Dist: flake8>=5.0.4; extra == "dev"
Requires-Dist: isort>=5.10.1; extra == "dev"
Requires-Dist: flake8-pyproject>=1.2.3; extra == "dev"
